{
    "components": [
        {
            "procedural": {
                "name": "fan",
                "mesh_type": "triangle_fan",
                "settings": {
                    "size": 10,
                    "coordinates": {
                        "name": "vertices",
                        "radius": 2.0,
                        "degrees": [0.0,180.0]
                    }
                }
            }
        },
        {
            "procedural": {
                "name": "disk",
                "mesh_type": "disk",
                "settings": {
                    "size": 10,
                    "coordinates": {
                        "name": "vertices",
                        "radius": 2.0
                    }
                }
            }
        },
        {
            "multimesh": {
                "parent": "disk",
                "child": "fan",
                "name": "mm"
            }
        },
        {
            "get_all_meshes": {
                "input": "mm",
                "name": "meshes"
            }
        },
        {
            "output": {
                "input": "meshes_",
                "file": "main",
                "attributes": {
                    "position": "vertices"
                }
            }
        },
        {
            "output": {
                "input": "meshes_0",
                "file": "uv",
                "attributes": {
                    "position": "vertices"
                }
            }
        }
    ]
}
